dbvirus_cacher/__init__.py
dbvirus_cacher/documents.py
dbvirus_cacher-0.0.4.dist-info/WHEEL
dbvirus_cacher-0.0.4.dist-info/METADATA
dbvirus_cacher-0.0.4.dist-info/RECORD
