Metadata-Version: 2.1
Name: dbvirus-cacher
Version: 0.0.4
Summary: 
Author: Felipe Rodrigues
Author-email: felipe@felipevr.com
Requires-Python: >=3.7,<4.0
Classifier: Programming Language :: Python :: 3
Classifier: Programming Language :: Python :: 3.7
Requires-Dist: mongoengine (>=0.18.2,<0.19.0)
Requires-Dist: pymongo (>=3.9,<4.0)
Requires-Dist: pytz (>=2019.3,<2020.0)
